corae/__init__.py
corae-0.0.1.dist-info/LICENSE
corae-0.0.1.dist-info/METADATA
corae-0.0.1.dist-info/WHEEL
corae-0.0.1.dist-info/top_level.txt
corae-0.0.1.dist-info/RECORD
